authenticator/__init__.py
authenticator/dataflowairflowauthenticator.py
authenticator/dataflowhubauthenticator.py
authenticator/dataflowsupersetauthenticator.py
authenticator/package/__init__.py
authenticator/package/configuration.py
authenticator/package/models/__init__.py
authenticator/package/models/database.py
authenticator/package/models/session.py
authenticator/package/models/user.py
dataflow/__init__.py
dataflow/configuration.py
dataflow/dataflow.py
dataflow/environment.py
dataflow/models/__init__.py
dataflow/models/database.py
dataflow/models/environment.py
dataflow/scripts/clone_environment.sh
dataflow/scripts/create_environment.sh
dataflow/utils/__init__.py
dataflow/utils/aws_secrets_manager.py
dataflow/utils/json_handler.py
test_dataflow_core-2.0.35.dist-info/METADATA
test_dataflow_core-2.0.35.dist-info/WHEEL
test_dataflow_core-2.0.35.dist-info/entry_points.txt
test_dataflow_core-2.0.35.dist-info/top_level.txt
test_dataflow_core-2.0.35.dist-info/RECORD
