Metadata-Version: 2.4
Name: test-dataflow-core
Version: 2.0.35
Summary: Dataflow core package
Author: Dataflow
Author-email: 
Requires-Dist: sqlalchemy
Requires-Dist: boto3
Requires-Dist: psycopg2-binary
Requires-Dist: pymysql
Requires-Dist: requests
Dynamic: author
Dynamic: requires-dist
Dynamic: summary
